odoo/addons/ssi_account_amortization/README.rst
odoo/addons/ssi_account_amortization/__init__.py
odoo/addons/ssi_account_amortization/__manifest__.py
odoo/addons/ssi_account_amortization/data/approval_template_data.xml
odoo/addons/ssi_account_amortization/data/base_automation_data.xml
odoo/addons/ssi_account_amortization/data/ir_actions_server_data.xml
odoo/addons/ssi_account_amortization/data/ir_sequence_data.xml
odoo/addons/ssi_account_amortization/data/policy_template_data.xml
odoo/addons/ssi_account_amortization/data/sequence_template_data.xml
odoo/addons/ssi_account_amortization/demo/account_account_demo.xml
odoo/addons/ssi_account_amortization/demo/account_journal_demo.xml
odoo/addons/ssi_account_amortization/demo/amortization_type_demo.xml
odoo/addons/ssi_account_amortization/i18n/ssi_account_amortization.pot
odoo/addons/ssi_account_amortization/models/__init__.py
odoo/addons/ssi_account_amortization/models/account_amortization.py
odoo/addons/ssi_account_amortization/models/amortization_schedule.py
odoo/addons/ssi_account_amortization/models/amortization_type.py
odoo/addons/ssi_account_amortization/models/res_company.py
odoo/addons/ssi_account_amortization/models/res_config_settings.py
odoo/addons/ssi_account_amortization/security/ir.model.access.csv
odoo/addons/ssi_account_amortization/security/ir_module_category_data.xml
odoo/addons/ssi_account_amortization/security/res_group_data.xml
odoo/addons/ssi_account_amortization/static/description/banner.png
odoo/addons/ssi_account_amortization/static/description/icon.png
odoo/addons/ssi_account_amortization/views/amortization_type_views.xml
odoo/addons/ssi_account_amortization/views/amortization_views.xml
odoo/addons/ssi_account_amortization/views/res_config_settings_views.xml
odoo14_addon_ssi_account_amortization-14.0.2.2.0.dist-info/METADATA
odoo14_addon_ssi_account_amortization-14.0.2.2.0.dist-info/WHEEL
odoo14_addon_ssi_account_amortization-14.0.2.2.0.dist-info/top_level.txt
odoo14_addon_ssi_account_amortization-14.0.2.2.0.dist-info/RECORD
